hxid/__init__.py
hxid/main.py
hxid-0.1.1.dist-info/LICENSE
hxid-0.1.1.dist-info/METADATA
hxid-0.1.1.dist-info/WHEEL
hxid-0.1.1.dist-info/top_level.txt
hxid-0.1.1.dist-info/RECORD
